chatgpt_to_md/__init__.py
chatgpt_to_md/core.py
chatgpt_to_md-0.1.0.dist-info/METADATA
chatgpt_to_md-0.1.0.dist-info/WHEEL
chatgpt_to_md-0.1.0.dist-info/entry_points.txt
chatgpt_to_md-0.1.0.dist-info/top_level.txt
chatgpt_to_md-0.1.0.dist-info/RECORD
